easyqc-1.1.0.dist-info/METADATA
easyqc-1.1.0.dist-info/WHEEL
easyqc-1.1.0.dist-info/entry_points.txt
easyqc-1.1.0.dist-info/licenses/LICENSE
easyqc/__init__.py
easyqc/easyqc.svg
easyqc/easyqc.ui
easyqc/gui.py
easyqc/pgtools.py
easyqc/qt.py
easyqc/spectrogram.ui
easyqc/tests/tests_model.py
easyqc/tests/tests_pgtools.py
easyqc-1.1.0.dist-info/RECORD
