Metadata-Version: 2.1
Name: easyqc
Version: 1.1.0
Summary: Seismic viewer for numpy
Author: Olivier Winter
Classifier: License :: OSI Approved :: MIT License
Classifier: Operating System :: OS Independent
Classifier: Programming Language :: Python :: 3
Project-URL: Homepage, https://github.com/oliche/easyqc
Project-URL: Bug Tracker, https://github.com/oliche/easyqc/issues
Requires-Python: >=3.8
Requires-Dist: PyQt5
Requires-Dist: numpy
Requires-Dist: pyqtgraph>=0.13.1
Requires-Dist: scipy
